Workbook

Sheet RESUMO
A1: CÓDIGO BARRAS | B1: DESCRIÇÃO | C1: CD | G1: PB1 | K1: PB2 | O1: PB3 | S1: ALTERAÇOES DE PREÇOS
C2: FARDO | D2: QTD DE FARDO | E2: ESTOQUE CD | F2: SALDO FINAL ESTOQUE | G2: ESTOQUE LOJA | H2: ESTOQUE MINIMO | I2: QUANTO ENVIAR ? | J2: SEPARAR | K2: ESTOQUE LOJA | L2: ESTOQUE MINIMO | M2: QUANTO ENVIAR ? | N2: SEPARAR | O2: ESTOQUE LOJA | P2: ESTOQUE MINIMO | Q2: QUANTO ENVIAR ? | R2: SEPARAR | S2: CUSTO UN | T2: PB1 | U2: % LUCRO | V2: PB2 | W2: % LUCRO | X2: PB3 | Y2: % LUCRO
D3: ='PB1'!H3+'PB2'!G3+'PB3'!G3 -> #DIV/0! | F3: =MAX((E3-SUM(J3,N3,R3))) -> 0 | I3: =G3-H3 -> 0 | M3: =K3-L3 -> 0 | Q3: =O3-P3 -> 0 | U3: =SUM(T3/S3)-1 -> #DIV/0! | W3: =SUM(V3/S3)-1 -> #DIV/0! | Y3: =SUM(X3/S3)-1 -> #DIV/0!
D4: ='PB1'!H4+'PB2'!G4+'PB3'!G4 -> #DIV/0! | F4: =MAX((E4-SUM(J4,N4,R4))) -> 0 | I4: =G4-H4 -> 0 | M4: =K4-L4 -> 0 | Q4: =O4-P4 -> 0 | U4: =SUM(T4/S4)-1 -> #DIV/0! | W4: =SUM(V4/S4)-1 -> #DIV/0! | Y4: =SUM(X4/S4)-1 -> #DIV/0!
D5: ='PB1'!H5+'PB2'!G5+'PB3'!G5 -> #DIV/0! | F5: =MAX((E5-SUM(J5,N5,R5))) -> 0 | I5: =G5-H5 -> 0 | M5: =K5-L5 -> 0 | Q5: =O5-P5 -> 0 | U5: =SUM(T5/S5)-1 -> #DIV/0! | W5: =SUM(V5/S5)-1 -> #DIV/0! | Y5: =SUM(X5/S5)-1 -> #DIV/0!
D6: ='PB1'!H6+'PB2'!G6+'PB3'!G6 -> #DIV/0! | F6: =MAX((E6-SUM(J6,N6,R6))) -> 0 | I6: =G6-H6 -> 0 | M6: =K6-L6 -> 0 | Q6: =O6-P6 -> 0 | U6: =SUM(T6/S6)-1 -> #DIV/0! | W6: =SUM(V6/S6)-1 -> #DIV/0! | Y6: =SUM(X6/S6)-1 -> #DIV/0!
D7: ='PB1'!H7+'PB2'!G7+'PB3'!G7 -> #DIV/0! | F7: =MAX((E7-SUM(J7,N7,R7))) -> 0 | I7: =G7-H7 -> 0 | M7: =K7-L7 -> 0 | Q7: =O7-P7 -> 0 | U7: =SUM(T7/S7)-1 -> #DIV/0! | W7: =SUM(V7/S7)-1 -> #DIV/0! | Y7: =SUM(X7/S7)-1 -> #DIV/0!
D8: ='PB1'!H8+'PB2'!G8+'PB3'!G8 -> #DIV/0! | F8: =MAX((E8-SUM(J8,N8,R8))) -> 0 | I8: =G8-H8 -> 0 | M8: =K8-L8 -> 0 | Q8: =O8-P8 -> 0 | U8: =SUM(T8/S8)-1 -> #DIV/0! | W8: =SUM(V8/S8)-1 -> #DIV/0! | Y8: =SUM(X8/S8)-1 -> #DIV/0!
D9: ='PB1'!H9+'PB2'!G9+'PB3'!G9 -> #DIV/0! | F9: =MAX((E9-SUM(J9,N9,R9))) -> 0 | I9: =G9-H9 -> 0 | M9: =K9-L9 -> 0 | Q9: =O9-P9 -> 0 | U9: =SUM(T9/S9)-1 -> #DIV/0! | W9: =SUM(V9/S9)-1 -> #DIV/0! | Y9: =SUM(X9/S9)-1 -> #DIV/0!
D10: ='PB1'!H10+'PB2'!G10+'PB3'!G10 -> #DIV/0! | F10: =MAX((E10-SUM(J10,N10,R10))) -> 0 | I10: =G10-H10 -> 0 | M10: =K10-L10 -> 0 | Q10: =O10-P10 -> 0 | U10: =SUM(T10/S10)-1 -> #DIV/0! | W10: =SUM(V10/S10)-1 -> #DIV/0! | Y10: =SUM(X10/S10)-1 -> #DIV/0!
D11: ='PB1'!H11+'PB2'!G11+'PB3'!G11 -> #DIV/0! | F11: =MAX((E11-SUM(J11,N11,R11))) -> 0 | I11: =G11-H11 -> 0 | M11: =K11-L11 -> 0 | Q11: =O11-P11 -> 0 | U11: =SUM(T11/S11)-1 -> #DIV/0! | W11: =SUM(V11/S11)-1 -> #DIV/0! | Y11: =SUM(X11/S11)-1 -> #DIV/0!
D12: ='PB1'!H12+'PB2'!G12+'PB3'!G12 -> #DIV/0! | F12: =MAX((E12-SUM(J12,N12,R12))) -> 0 | I12: =G12-H12 -> 0 | M12: =K12-L12 -> 0 | Q12: =O12-P12 -> 0 | U12: =SUM(T12/S12)-1 -> #DIV/0! | W12: =SUM(V12/S12)-1 -> #DIV/0! | Y12: =SUM(X12/S12)-1 -> #DIV/0!
D13: ='PB1'!H13+'PB2'!G13+'PB3'!G13 -> #DIV/0! | F13: =MAX((E13-SUM(J13,N13,R13))) -> 0 | I13: =G13-H13 -> 0 | M13: =K13-L13 -> 0 | Q13: =O13-P13 -> 0 | U13: =SUM(T13/S13)-1 -> #DIV/0! | W13: =SUM(V13/S13)-1 -> #DIV/0! | Y13: =SUM(X13/S13)-1 -> #DIV/0!
D14: ='PB1'!H14+'PB2'!G14+'PB3'!G14 -> #DIV/0! | F14: =MAX((E14-SUM(J14,N14,R14))) -> 0 | I14: =G14-H14 -> 0 | M14: =K14-L14 -> 0 | Q14: =O14-P14 -> 0 | U14: =SUM(T14/S14)-1 -> #DIV/0! | W14: =SUM(V14/S14)-1 -> #DIV/0! | Y14: =SUM(X14/S14)-1 -> #DIV/0!
... D101: ='PB1'!H101+'PB2'!G101+'PB3'!G101 -> #DIV/0! | F101: =MAX((E101-SUM(J101,N101,R101))) -> 0 | I101: =G101-H101 -> 0 | M101: =K101-L101 -> 0 | Q101: =O101-P101 -> 0 | U101: =SUM(T101/S101)-1 -> #DIV/0! | W101: =SUM(V101/S101)-1 -> #DIV/0! | Y101: =SUM(X101/S101)-1 -> #DIV/0!
D102: ='PB1'!H102+'PB2'!G102+'PB3'!G102 -> 0 | U102: =SUM(T102/S102)-1 -> #DIV/0! | W102: =SUM(V102/S102)-1 -> #DIV/0! | Y102: =SUM(X102/S102)-1 -> #DIV/0!
D103: ='PB1'!H103+'PB2'!G103+'PB3'!G103 -> 0 | U103: =SUM(T103/S103)-1 -> #DIV/0! | W103: =SUM(V103/S103)-1 -> #DIV/0! | Y103: =SUM(X103/S103)-1 -> #DIV/0!
D104: ='PB1'!H104+'PB2'!G104+'PB3'!G104 -> 0 | U104: =SUM(T104/S104)-1 -> #DIV/0! | W104: =SUM(V104/S104)-1 -> #DIV/0! | Y104: =SUM(X104/S104)-1 -> #DIV/0!
D105: ='PB1'!H105+'PB2'!G105+'PB3'!G105 -> 0 | U105: =SUM(T105/S105)-1 -> #DIV/0! | W105: =SUM(V105/S105)-1 -> #DIV/0! | Y105: =SUM(X105/S105)-1 -> #DIV/0!
D106: ='PB1'!H106+'PB2'!G106+'PB3'!G106 -> 0 | U106: =SUM(T106/S106)-1 -> #DIV/0! | W106: =SUM(V106/S106)-1 -> #DIV/0! | Y106: =SUM(X106/S106)-1 -> #DIV/0!
D107: ='PB1'!H107+'PB2'!G107+'PB3'!G107 -> 0 | U107: =SUM(T107/S107)-1 -> #DIV/0! | W107: =SUM(V107/S107)-1 -> #DIV/0! | Y107: =SUM(X107/S107)-1 -> #DIV/0!
D108: ='PB1'!H108+'PB2'!G108+'PB3'!G108 -> 0 | U108: =SUM(T108/S108)-1 -> #DIV/0! | W108: =SUM(V108/S108)-1 -> #DIV/0! | Y108: =SUM(X108/S108)-1 -> #DIV/0!
D109: ='PB1'!H109+'PB2'!G109+'PB3'!G109 -> 0 | U109: =SUM(T109/S109)-1 -> #DIV/0! | W109: =SUM(V109/S109)-1 -> #DIV/0! | Y109: =SUM(X109/S109)-1 -> #DIV/0!
D110: ='PB1'!H110+'PB2'!G110+'PB3'!G110 -> 0 | U110: =SUM(T110/S110)-1 -> #DIV/0! | W110: =SUM(V110/S110)-1 -> #DIV/0! | Y110: =SUM(X110/S110)-1 -> #DIV/0!
D111: ='PB1'!H111+'PB2'!G111+'PB3'!G111 -> 0 | U111: =SUM(T111/S111)-1 -> #DIV/0! | W111: =SUM(V111/S111)-1 -> #DIV/0! | Y111: =SUM(X111/S111)-1 -> #DIV/0!
D112: ='PB1'!H112+'PB2'!G112+'PB3'!G112 -> 0 | U112: =SUM(T112/S112)-1 -> #DIV/0! | W112: =SUM(V112/S112)-1 -> #DIV/0! | Y112: =SUM(X112/S112)-1 -> #DIV/0!
D113: ='PB1'!H113+'PB2'!G113+'PB3'!G113 -> 0 | U113: =SUM(T113/S113)-1 -> #DIV/0! | W113: =SUM(V113/S113)-1 -> #DIV/0! | Y113: =SUM(X113/S113)-1 -> #DIV/0!
... D3993: ='PB1'!H3993+'PB2'!G3993+'PB3'!G3993 -> 0 | U3993: =SUM(T3993/S3993)-1 -> #DIV/0! | W3993: =SUM(V3993/S3993)-1 -> #DIV/0! | Y3993: =SUM(X3993/S3993)-1 -> #DIV/0!

Sheet PB1
A1: PB1
A2: PRODUTO | B2: ENVIAR | C2: SEPARADO | D2: RECEBIDO | E2: PREÇO UN | F2: PREÇO VENDA | G2: FARDO | H2: FARDO
A3: =RESUMO!B3 -> 0 | B3: =RESUMO!J3 -> 0 | E3: =RESUMO!S3 -> 0 | F3: =RESUMO!T3 -> 0 | G3: =RESUMO!#REF! -> #REF! | H3: =RESUMO!J3/RESUMO!C3 -> #DIV/0!
A4: =RESUMO!B4 -> 0 | B4: =RESUMO!J4 -> 0 | E4: =RESUMO!S4 -> 0 | F4: =RESUMO!T4 -> 0 | G4: =RESUMO!#REF! -> #REF! | H4: =RESUMO!J4/RESUMO!C4 -> #DIV/0!
A5: =RESUMO!B5 -> 0 | B5: =RESUMO!J5 -> 0 | E5: =RESUMO!S5 -> 0 | F5: =RESUMO!T5 -> 0 | G5: =RESUMO!#REF! -> #REF! | H5: =RESUMO!J5/RESUMO!C5 -> #DIV/0!
A6: =RESUMO!B6 -> 0 | B6: =RESUMO!J6 -> 0 | E6: =RESUMO!S6 -> 0 | F6: =RESUMO!T6 -> 0 | G6: =RESUMO!#REF! -> #REF! | H6: =RESUMO!J6/RESUMO!C6 -> #DIV/0!
A7: =RESUMO!B7 -> 0 | B7: =RESUMO!J7 -> 0 | E7: =RESUMO!S7 -> 0 | F7: =RESUMO!T7 -> 0 | G7: =RESUMO!#REF! -> #REF! | H7: =RESUMO!J7/RESUMO!C7 -> #DIV/0!
A8: =RESUMO!B8 -> 0 | B8: =RESUMO!J8 -> 0 | E8: =RESUMO!S8 -> 0 | F8: =RESUMO!T8 -> 0 | G8: =RESUMO!#REF! -> #REF! | H8: =RESUMO!J8/RESUMO!C8 -> #DIV/0!
A9: =RESUMO!B9 -> 0 | B9: =RESUMO!J9 -> 0 | E9: =RESUMO!S9 -> 0 | F9: =RESUMO!T9 -> 0 | G9: =RESUMO!#REF! -> #REF! | H9: =RESUMO!J9/RESUMO!C9 -> #DIV/0!
A10: =RESUMO!B10 -> 0 | B10: =RESUMO!J10 -> 0 | E10: =RESUMO!S10 -> 0 | F10: =RESUMO!T10 -> 0 | G10: =RESUMO!#REF! -> #REF! | H10: =RESUMO!J10/RESUMO!C10 -> #DIV/0!
A11: =RESUMO!B11 -> 0 | B11: =RESUMO!J11 -> 0 | E11: =RESUMO!S11 -> 0 | F11: =RESUMO!T11 -> 0 | G11: =RESUMO!#REF! -> #REF! | H11: =RESUMO!J11/RESUMO!C11 -> #DIV/0!
A12: =RESUMO!B12 -> 0 | B12: =RESUMO!J12 -> 0 | E12: =RESUMO!S12 -> 0 | F12: =RESUMO!T12 -> 0 | G12: =RESUMO!#REF! -> #REF! | H12: =RESUMO!J12/RESUMO!C12 -> #DIV/0!
A13: =RESUMO!B13 -> 0 | B13: =RESUMO!J13 -> 0 | E13: =RESUMO!S13 -> 0 | F13: =RESUMO!T13 -> 0 | G13: =RESUMO!#REF! -> #REF! | H13: =RESUMO!J13/RESUMO!C13 -> #DIV/0!
A14: =RESUMO!B14 -> 0 | B14: =RESUMO!J14 -> 0 | E14: =RESUMO!S14 -> 0 | F14: =RESUMO!T14 -> 0 | G14: =RESUMO!#REF! -> #REF! | H14: =RESUMO!J14/RESUMO!C14 -> #DIV/0!
... A86: =RESUMO!B86 -> 0 | B86: =RESUMO!J86 -> 0 | E86: =RESUMO!S86 -> 0 | F86: =RESUMO!T86 -> 0 | G86: =RESUMO!#REF! -> #REF! | H86: =RESUMO!J86/RESUMO!C86 -> #DIV/0!
A88: data: 19/06/2026

Sheet PB2
A1: PB2
A2: PRODUTO | B2: ENVIAR | C2: SEPARADO | D2: RECEBIDO | E2: PREÇO UN | F2: PREÇO VENDA | G2: FARDO
A3: =RESUMO!B3 -> 0 | B3: =RESUMO!N3 -> 0 | E3: =RESUMO!S3 -> 0 | F3: =RESUMO!V3 -> 0 | G3: =RESUMO!N3/RESUMO!C3 -> #DIV/0!
A4: =RESUMO!B4 -> 0 | B4: =RESUMO!N4 -> 0 | E4: =RESUMO!S4 -> 0 | F4: =RESUMO!V4 -> 0 | G4: =RESUMO!N4/RESUMO!C4 -> #DIV/0!
A5: =RESUMO!B5 -> 0 | B5: =RESUMO!N5 -> 0 | E5: =RESUMO!S5 -> 0 | F5: =RESUMO!V5 -> 0 | G5: =RESUMO!N5/RESUMO!C5 -> #DIV/0!
A6: =RESUMO!B6 -> 0 | B6: =RESUMO!N6 -> 0 | E6: =RESUMO!S6 -> 0 | F6: =RESUMO!V6 -> 0 | G6: =RESUMO!N6/RESUMO!C6 -> #DIV/0!
A7: =RESUMO!B7 -> 0 | B7: =RESUMO!N7 -> 0 | E7: =RESUMO!S7 -> 0 | F7: =RESUMO!V7 -> 0 | G7: =RESUMO!N7/RESUMO!C7 -> #DIV/0!
A8: =RESUMO!B8 -> 0 | B8: =RESUMO!N8 -> 0 | E8: =RESUMO!S8 -> 0 | F8: =RESUMO!V8 -> 0 | G8: =RESUMO!N8/RESUMO!C8 -> #DIV/0!
A9: =RESUMO!B9 -> 0 | B9: =RESUMO!N9 -> 0 | E9: =RESUMO!S9 -> 0 | F9: =RESUMO!V9 -> 0 | G9: =RESUMO!N9/RESUMO!C9 -> #DIV/0!
A10: =RESUMO!B10 -> 0 | B10: =RESUMO!N10 -> 0 | E10: =RESUMO!S10 -> 0 | F10: =RESUMO!V10 -> 0 | G10: =RESUMO!N10/RESUMO!C10 -> #DIV/0!
A11: =RESUMO!B11 -> 0 | B11: =RESUMO!N11 -> 0 | E11: =RESUMO!S11 -> 0 | F11: =RESUMO!V11 -> 0 | G11: =RESUMO!N11/RESUMO!C11 -> #DIV/0!
A12: =RESUMO!B12 -> 0 | B12: =RESUMO!N12 -> 0 | E12: =RESUMO!S12 -> 0 | F12: =RESUMO!V12 -> 0 | G12: =RESUMO!N12/RESUMO!C12 -> #DIV/0!
A13: =RESUMO!B13 -> 0 | B13: =RESUMO!N13 -> 0 | E13: =RESUMO!S13 -> 0 | F13: =RESUMO!V13 -> 0 | G13: =RESUMO!N13/RESUMO!C13 -> #DIV/0!
A14: =RESUMO!B14 -> 0 | B14: =RESUMO!N14 -> 0 | E14: =RESUMO!S14 -> 0 | F14: =RESUMO!V14 -> 0 | G14: =RESUMO!N14/RESUMO!C14 -> #DIV/0!
... A101: =RESUMO!B101 -> 0 | B101: =RESUMO!N101 -> 0 | E101: =RESUMO!S101 -> 0 | F101: =RESUMO!V101 -> 0 | G101: =RESUMO!N101/RESUMO!C101 -> #DIV/0!

Sheet PB3
A1: PB3
A2: PRODUTO | B2: ENVIAR | C2: SEPARADO | D2: RECEBIDO | E2: PREÇO UN | F2: PREÇO VENDA | G2: FARDO
A3: =RESUMO!B3 -> 0 | B3: =RESUMO!R3 -> 0 | E3: =RESUMO!S3 -> 0 | F3: =RESUMO!X3 -> 0 | G3: =RESUMO!R3/RESUMO!C3 -> #DIV/0!
A4: =RESUMO!B4 -> 0 | B4: =RESUMO!R4 -> 0 | E4: =RESUMO!S4 -> 0 | F4: =RESUMO!X4 -> 0 | G4: =RESUMO!R4/RESUMO!C4 -> #DIV/0!
A5: =RESUMO!B5 -> 0 | B5: =RESUMO!R5 -> 0 | E5: =RESUMO!S5 -> 0 | F5: =RESUMO!X5 -> 0 | G5: =RESUMO!R5/RESUMO!C5 -> #DIV/0!
A6: =RESUMO!B6 -> 0 | B6: =RESUMO!R6 -> 0 | E6: =RESUMO!S6 -> 0 | F6: =RESUMO!X6 -> 0 | G6: =RESUMO!R6/RESUMO!C6 -> #DIV/0!
A7: =RESUMO!B7 -> 0 | B7: =RESUMO!R7 -> 0 | E7: =RESUMO!S7 -> 0 | F7: =RESUMO!X7 -> 0 | G7: =RESUMO!R7/RESUMO!C7 -> #DIV/0!
A8: =RESUMO!B8 -> 0 | B8: =RESUMO!R8 -> 0 | E8: =RESUMO!S8 -> 0 | F8: =RESUMO!X8 -> 0 | G8: =RESUMO!R8/RESUMO!C8 -> #DIV/0!
A9: =RESUMO!B9 -> 0 | B9: =RESUMO!R9 -> 0 | E9: =RESUMO!S9 -> 0 | F9: =RESUMO!X9 -> 0 | G9: =RESUMO!R9/RESUMO!C9 -> #DIV/0!
A10: =RESUMO!B10 -> 0 | B10: =RESUMO!R10 -> 0 | E10: =RESUMO!S10 -> 0 | F10: =RESUMO!X10 -> 0 | G10: =RESUMO!R10/RESUMO!C10 -> #DIV/0!
A11: =RESUMO!B11 -> 0 | B11: =RESUMO!R11 -> 0 | E11: =RESUMO!S11 -> 0 | F11: =RESUMO!X11 -> 0 | G11: =RESUMO!R11/RESUMO!C11 -> #DIV/0!
A12: =RESUMO!B12 -> 0 | B12: =RESUMO!R12 -> 0 | E12: =RESUMO!S12 -> 0 | F12: =RESUMO!X12 -> 0 | G12: =RESUMO!R12/RESUMO!C12 -> #DIV/0!
A13: =RESUMO!B13 -> 0 | B13: =RESUMO!R13 -> 0 | E13: =RESUMO!S13 -> 0 | F13: =RESUMO!X13 -> 0 | G13: =RESUMO!R13/RESUMO!C13 -> #DIV/0!
A14: =RESUMO!B14 -> 0 | B14: =RESUMO!R14 -> 0 | E14: =RESUMO!S14 -> 0 | F14: =RESUMO!X14 -> 0 | G14: =RESUMO!R14/RESUMO!C14 -> #DIV/0!
... A101: =RESUMO!B101 -> 0 | B101: =RESUMO!R101 -> 0 | E101: =RESUMO!S101 -> 0 | F101: =RESUMO!X101 -> 0 | G101: =RESUMO!R101/RESUMO!C101 -> #DIV/0!
